badgify/__init__.py
badgify/admin.py
badgify/apps.py
badgify/commands.py
badgify/compat.py
badgify/exceptions.py
badgify/recipe.py
badgify/registry.py
badgify/settings.py
badgify/signals.py
badgify/urls.py
badgify/utils.py
badgify/views.py
badgify/management/__init__.py
badgify/management/commands/__init__.py
badgify/management/commands/badgify_reset.py
badgify/management/commands/badgify_stats.py
badgify/management/commands/badgify_sync.py
badgify/migrations/0001_initial.py
badgify/migrations/__init__.py
badgify/models/__init__.py
badgify/models/award.py
badgify/models/badge.py
badgify/models/base/__init__.py
badgify/models/base/award.py
badgify/models/base/badge.py
badgify/templatetags/__init__.py
badgify/templatetags/badgify_tags.py
badgify/tests/__init__.py
badgify/tests/badgify_recipes.py
badgify/tests/mixins.py
badgify/tests/models.py
badgify/tests/recipes.py
badgify/tests/settings.py
badgify/tests/test_commands.py
badgify/tests/test_models.py
badgify/tests/test_registry.py
badgify/tests/test_templatetags.py
badgify/tests/test_views.py
django_badgify_lab-0.2.0.dist-info/DESCRIPTION.rst
django_badgify_lab-0.2.0.dist-info/METADATA
django_badgify_lab-0.2.0.dist-info/RECORD
django_badgify_lab-0.2.0.dist-info/WHEEL
django_badgify_lab-0.2.0.dist-info/metadata.json
django_badgify_lab-0.2.0.dist-info/top_level.txt
example/__init__.py
example/admin.py
example/badgify_recipes.py
example/models.py
example/settings.py
example/urls.py
example/wsgi.py
example/management/__init__.py
example/management/commands/__init__.py
example/management/commands/create_fixtures.py
example/migrations/0001_initial.py
example/migrations/0002_auto_20170901_1827.py
example/migrations/__init__.py
