Metadata-Version: 2.0
Name: django-badgify-lab
Version: 0.2.0
Summary: A reusable application to create your own badge engine using Django
Home-page: http://github.com/ulule/django-badgify
Author: Gilles Fabio
Author-email: gilles.fabio@gmail.com
License: UNKNOWN
Platform: UNKNOWN
Classifier: Environment :: Web Environment
Classifier: Framework :: Django
Classifier: Intended Audience :: Developers
Classifier: License :: OSI Approved :: MIT License
Classifier: Operating System :: OS Independent
Classifier: Programming Language :: Python
Classifier: Programming Language :: Python :: 2.7
Classifier: Programming Language :: Python :: 3
Classifier: Programming Language :: Python :: 3.4
Classifier: Programming Language :: Python :: 3.5
Classifier: Topic :: Utilities
Requires-Dist: Pillow
Requires-Dist: pytz
Requires-Dist: six
